<?xml version="1.0" encoding="UTF-8" standalone="no"?>
<sfObject creatable="true" defaultCompactLayoutId="Task.SYSTEM" deleteable="true" keyPrefix="00T" label="Task" labelPlural="Tasks" layoutable="true" metadataLabel="Task" n="Task" queryable="true" retrieveable="true" s="" searchLayoutable="true" t="Task (00T)" updatable="true" urlDetail="/{ID}" urlEdit="/{ID}/e" urlNew="/00T/e">
  <fields>
    <sfField createable="false" editPermission="false" length="18" n="Id" t="Activity ID" type="id" updateable="false"/>
    <sfField length="18" n="WhoId" relationshipName="Who" t="Name" type="reference">
      <referenceTos>
        <string>Contact</string>
        <string>Lead</string>
      </referenceTos>
    </sfField>
    <sfField length="18" n="WhatId" relationshipName="What" t="Related To" type="reference">
      <referenceTos>
        <string>Account</string>
        <string>Account_Plan__c</string>
        <string>Agreement__c</string>
        <string>Asset</string>
        <string>AssetRelationship</string>
        <string>Associated_Orders__c</string>
        <string>B2CCommerceCloud_Internal_SF_Helpdesk__c</string>
        <string>BuyerAccount</string>
        <string>BuyerGroupPricebook</string>
        <string>CRMfusionDBR101__Duplicate_Warning__c</string>
        <string>Campaign</string>
        <string>Case</string>
        <string>Centennial_Campaign__c</string>
        <string>ChannelProgram</string>
        <string>ChannelProgramLevel</string>
        <string>Class_Instructor__c</string>
        <string>CommSubscriptionConsent</string>
        <string>ContactRequest</string>
        <string>Contract</string>
        <string>ContractLineItem</string>
        <string>Course_Catalog__c</string>
        <string>Dedicated_Internal_Salesforce_Helpdesk__c</string>
        <string>DelegatedAccount</string>
        <string>Entitlement</string>
        <string>Facility__c</string>
        <string>Free_Class__c</string>
        <string>IBP__Ifbyphone_Call__c</string>
        <string>Image</string>
        <string>Integration_Log__c</string>
        <string>LTS_Facility__c</string>
        <string>Lead__c</string>
        <string>ListEmail</string>
        <string>LiveAgentSession</string>
        <string>LiveChatTranscript</string>
        <string>Location</string>
        <string>Offering__c</string>
        <string>Opportunity</string>
        <string>Order</string>
        <string>PHSS_Instructor_Certification__c</string>
        <string>PHSS_Material__c</string>
        <string>PHSS_Program__c</string>
        <string>PartnerFundAllocation</string>
        <string>PartnerFundClaim</string>
        <string>PartnerFundRequest</string>
        <string>PartnerMarketingBudget</string>
        <string>PartyConsent</string>
        <string>ProcessException</string>
        <string>Product2</string>
        <string>ProductCatalog</string>
        <string>Promotion</string>
        <string>PromotionMarketSegment</string>
        <string>PromotionQualifier</string>
        <string>PromotionSegment</string>
        <string>PromotionSegmentBuyerGroup</string>
        <string>PromotionSegmentSalesStore</string>
        <string>PromotionTarget</string>
        <string>PurchaseQuantityRule</string>
        <string>Quote</string>
        <string>ReportCard__c</string>
        <string>SFDC_Budget__c</string>
        <string>SFDC_MDF_Claim__c</string>
        <string>SFDC_MDF__c</string>
        <string>SFSSDupeCatcher__Duplicate_Warning__c</string>
        <string>SFSSDupeCatcher__Potential_Duplicate__c</string>
        <string>SFSSDupeCatcher__Scenario__c</string>
        <string>Sales_Tax_Exemption__c</string>
        <string>ServiceContract</string>
        <string>Shipment</string>
        <string>ShipmentItem</string>
        <string>Skills_Achievement__c</string>
        <string>Solution</string>
        <string>SurveyQuestion</string>
        <string>Training_Events__c</string>
        <string>Virtual_Training_Student_Contact__c</string>
        <string>Voucher__c</string>
        <string>WebStorePricebook</string>
        <string>ccpgcs__E_PaymentType__c</string>
        <string>ccrz__E_AccountGroupPriceList__c</string>
        <string>ccrz__E_AccountGroup__c</string>
        <string>ccrz__E_AccountSetting__c</string>
        <string>ccrz__E_AddressBook__c</string>
        <string>ccrz__E_CartItem__c</string>
        <string>ccrz__E_Cart__c</string>
        <string>ccrz__E_Category__c</string>
        <string>ccrz__E_CompositeProduct__c</string>
        <string>ccrz__E_ContactAddr__c</string>
        <string>ccrz__E_Coupon__c</string>
        <string>ccrz__E_Invoice__c</string>
        <string>ccrz__E_OrderItem__c</string>
        <string>ccrz__E_OrderShipmentItem__c</string>
        <string>ccrz__E_OrderShipment__c</string>
        <string>ccrz__E_Order__c</string>
        <string>ccrz__E_PageSection__c</string>
        <string>ccrz__E_PriceGroupAccount__c</string>
        <string>ccrz__E_PriceGroupItem__c</string>
        <string>ccrz__E_PriceGroupPricelist__c</string>
        <string>ccrz__E_PriceGroup__c</string>
        <string>ccrz__E_PriceListItem__c</string>
        <string>ccrz__E_PriceList__c</string>
        <string>ccrz__E_PriceModifier__c</string>
        <string>ccrz__E_ProductInventoryItem__c</string>
        <string>ccrz__E_ProductMedia__c</string>
        <string>ccrz__E_ProductTab__c</string>
        <string>ccrz__E_Product__c</string>
        <string>ccrz__E_Promo__c</string>
        <string>ccrz__E_RecentItem__c</string>
        <string>ccrz__E_RelatedProduct__c</string>
        <string>ccrz__E_Review__c</string>
        <string>ccrz__E_RulePricingModifier__c</string>
        <string>ccrz__E_RuleTargetSKU__c</string>
        <string>ccrz__E_Rule__c</string>
        <string>ccrz__E_Spec__c</string>
        <string>ccrz__E_StorefrontConfigSettings__c</string>
        <string>ccrz__E_SubProdTerm__c</string>
        <string>ccrz__E_Subscription__c</string>
        <string>ccrz__E_TaxRate__c</string>
        <string>cwbtool__AnalysisSummary__c</string>
        <string>cwbtool__Component__c</string>
        <string>cwbtool__FieldTrack__c</string>
        <string>dsfs__DocuSign_Recipient_Status__c</string>
        <string>dsfs__DocuSign_Status__c</string>
        <string>jurisdiction__c</string>
        <string>redwing__Achievement_Category__c</string>
        <string>redwing__Achievement__c</string>
        <string>redwing__Answer_Sequence_Item__c</string>
        <string>redwing__Answer_Sequence__c</string>
        <string>redwing__CheckIn__c</string>
        <string>redwing__ILT_Roster__c</string>
        <string>redwing__Instructor__c</string>
        <string>redwing__LMS_Permission_Rule_PermSet__c</string>
        <string>redwing__LMS_Permission_Rule__c</string>
        <string>redwing__LMS_Plugin__c</string>
        <string>redwing__Learning_Assignment__c</string>
        <string>redwing__Learning_Category_Account__c</string>
        <string>redwing__Learning_Category_Profile__c</string>
        <string>redwing__Learning_Category__c</string>
        <string>redwing__Learning_Search_Category_Item__c</string>
        <string>redwing__Learning_Search_Category__c</string>
        <string>redwing__Learning_Version__c</string>
        <string>redwing__Learning__c</string>
        <string>redwing__Question_Bank_Question__c</string>
        <string>redwing__Question_Bank__c</string>
        <string>redwing__Question_Line__c</string>
        <string>redwing__Question_Topic__c</string>
        <string>redwing__Question__c</string>
        <string>redwing__Quiz__c</string>
        <string>redwing__Response__c</string>
        <string>redwing__RichText_Content__c</string>
        <string>redwing__RichText__c</string>
        <string>redwing__Shared_Learning_Assignment__c</string>
        <string>redwing__Task_Approver__c</string>
        <string>redwing__Task__c</string>
        <string>redwing__Training_Activity_Account__c</string>
        <string>redwing__Training_Activity_Category__c</string>
        <string>redwing__Training_Activity_Search_Category_Item__c</string>
        <string>redwing__Training_Activity__c</string>
        <string>redwing__Training_Plan_Access_Request__c</string>
        <string>redwing__Training_Plan_Account__c</string>
        <string>redwing__Training_Plan_Achievement__c</string>
        <string>redwing__Training_Plan_Assignment__c</string>
        <string>redwing__Training_Plan_Batch_Operation__c</string>
        <string>redwing__Training_Plan_Category__c</string>
        <string>redwing__Training_Plan_Feedback__c</string>
        <string>redwing__Training_Plan_Instructor__c</string>
        <string>redwing__Training_Plan_Search_Category_Item__c</string>
        <string>redwing__Training_Plan_Section_Assignment__c</string>
        <string>redwing__Training_Plan_Section_Item__c</string>
        <string>redwing__Training_Plan_Section__c</string>
        <string>redwing__Training_Plan__c</string>
        <string>redwing__Training_Resource__c</string>
        <string>redwing__Training_Track_Account__c</string>
        <string>redwing__Training_Track_Assignment__c</string>
        <string>redwing__Training_Track_Category__c</string>
        <string>redwing__Training_Track_Level_Item__c</string>
        <string>redwing__Training_Track_Level__c</string>
        <string>redwing__Training_Track_Search_Category_Item__c</string>
        <string>redwing__Training_Track__c</string>
        <string>redwing__User_Certification__c</string>
        <string>scormanywhere__Course__c</string>
        <string>sked__Job__c</string>
        <string>sked__Location__c</string>
        <string>sked__Resource__c</string>
        <string>sked__Schedule_Template__c</string>
        <string>sked__Templated_Activity_Resource__c</string>
        <string>sked__Templated_Activity__c</string>
        <string>sked__Templated_Attendee__c</string>
        <string>sked__Templated_Job_Allocation__c</string>
        <string>sked__Templated_Job_Product__c</string>
        <string>sked__Templated_Job_Tag__c</string>
        <string>sked__Templated_Job_Task__c</string>
        <string>sked__Templated_Job_Time_Constraint__c</string>
        <string>sked__Templated_Job__c</string>
        <string>sked__Templated_Resource_Requirement_Tag__c</string>
        <string>sked__Templated_Resource_Requirement__c</string>
        <string>sked__Templated_Resource_Shift__c</string>
        <string>sked__Templated_Shift_Tag__c</string>
        <string>sked__Templated_Shift__c</string>
        <string>zkmulti__EEIForm__c</string>
        <string>zkmulti__MCBulk_Shipment__c</string>
        <string>zkmulti__MCPickup__c</string>
        <string>zkmulti__MCShipment__c</string>
      </referenceTos>
      <relatedListTranslationLabels/>
      <otherRelatedListTranslationLabels>
        <entry>
          <key valueClass="string">Task.WhatId</key>
          <value valueClass="string">Related To</value>
        </entry>
      </otherRelatedListTranslationLabels>
    </sfField>
    <sfField length="255" n="Subject" nameField="true" type="combobox">
      <picklistEntryIds>1,2,3,4,5</picklistEntryIds>
      <picklistEntries>
        <sfPLE id="1" n="Call" s=""/>
        <sfPLE id="2" n="Email" s=""/>
        <sfPLE id="3" n="Send Letter" s=""/>
        <sfPLE id="4" n="Send Quote" s=""/>
        <sfPLE id="5" n="Other" s=""/>
      </picklistEntries>
      <relatedListTranslationLabels/>
      <otherRelatedListTranslationLabels>
        <entry>
          <key valueClass="string">Activity.Subject</key>
          <value valueClass="string">Subject</value>
        </entry>
      </otherRelatedListTranslationLabels>
    </sfField>
    <sfField n="ActivityDate" t="Due Date" type="date">
      <relatedListTranslationLabels/>
      <otherRelatedListTranslationLabels>
        <entry>
          <key valueClass="string">Task.ActivityDate</key>
          <value valueClass="string">Due Date</value>
        </entry>
      </otherRelatedListTranslationLabels>
    </sfField>
    <sfField length="255" n="Status" standardPickListName="TaskStatus" type="picklist">
      <picklistEntryIds>6,7,8,9,10</picklistEntryIds>
      <picklistEntries>
        <sfPLE defaultValue="true" id="6" n="Not Started" s=""/>
        <sfPLE id="7" n="In Progress" s=""/>
        <sfPLE id="8" n="Completed" s=""/>
        <sfPLE id="9" n="Waiting on someone else" s=""/>
        <sfPLE id="10" n="Deferred" s=""/>
      </picklistEntries>
      <relatedListTranslationLabels/>
      <otherRelatedListTranslationLabels>
        <entry>
          <key valueClass="string">Task.Status</key>
          <value valueClass="string">Status</value>
        </entry>
      </otherRelatedListTranslationLabels>
    </sfField>
    <sfField length="20" n="Priority" standardPickListName="TaskPriority" type="picklist">
      <picklistEntryIds>11,12,13</picklistEntryIds>
      <picklistEntries>
        <sfPLE id="11" n="High" s=""/>
        <sfPLE defaultValue="true" id="12" n="Normal" s=""/>
        <sfPLE id="13" n="Low" s=""/>
      </picklistEntries>
      <relatedListTranslationLabels/>
      <otherRelatedListTranslationLabels>
        <entry>
          <key valueClass="string">Task.Priority</key>
          <value valueClass="string">Priority</value>
        </entry>
      </otherRelatedListTranslationLabels>
    </sfField>
    <sfField createable="false" editPermission="false" n="IsHighPriority" t="High Priority" type="_boolean" updateable="false"/>
    <sfField createable="false" digits="9" editPermission="false" n="PrioritySortOrder" readPermission="false" t="Priority Sort Order" type="_int" updateable="false"/>
    <sfField length="18" n="OwnerId" relationshipName="Owner" t="Assigned To" type="reference">
      <referenceTos>
        <string>Group</string>
        <string>User</string>
      </referenceTos>
    </sfField>
    <sfField extraTypeInfo="plaintextarea" filterable="false" length="32000" n="Description" t="Comments" type="textarea"/>
    <sfField length="255" n="Type" standardPickListName="TaskType" type="picklist">
      <picklistEntryIds>1,14,5,15</picklistEntryIds>
      <picklistEntries>
        <sfPLE id="1" n="Call" s=""/>
        <sfPLE id="14" n="Meeting" s=""/>
        <sfPLE id="5" n="Other" s=""/>
        <sfPLE id="15" n="face-to-facer-ers" s=""/>
      </picklistEntries>
    </sfField>
    <sfField createable="false" editPermission="false" n="IsDeleted" t="Deleted" type="_boolean" updateable="false"/>
    <sfField createable="false" length="18" n="AccountId" relationshipName="Account" t="Account" type="reference" updateable="false">
      <referenceTos>
        <string>Account</string>
      </referenceTos>
    </sfField>
    <sfField createable="false" editPermission="false" n="IsClosed" t="Closed" type="_boolean" updateable="false"/>
    <sfField createable="false" editPermission="false" n="CreatedDate" t="Created Date" type="datetime" updateable="false"/>
    <sfField createable="false" editPermission="false" length="18" n="CreatedById" relationshipName="CreatedBy" t="Created By" type="reference" updateable="false">
      <referenceTos>
        <string>User</string>
      </referenceTos>
    </sfField>
    <sfField createable="false" editPermission="false" n="LastModifiedDate" t="Last Modified Date" type="datetime" updateable="false">
      <relatedListTranslationLabels/>
      <otherRelatedListTranslationLabels>
        <entry>
          <key valueClass="string">Task.LastModifiedDate</key>
          <value valueClass="string">Last Modified Date/Time</value>
        </entry>
      </otherRelatedListTranslationLabels>
    </sfField>
    <sfField createable="false" editPermission="false" length="18" n="LastModifiedById" relationshipName="LastModifiedBy" t="Last Modified By" type="reference" updateable="false">
      <referenceTos>
        <string>User</string>
      </referenceTos>
    </sfField>
    <sfField createable="false" editPermission="false" n="SystemModstamp" t="System Modstamp" type="datetime" updateable="false"/>
    <sfField createable="false" editPermission="false" n="IsArchived" t="Archived" type="_boolean" updateable="false"/>
    <sfField createable="false" editPermission="false" n="ArchivedDate" readPermission="false" t="Archived Date" type="date" updateable="false"/>
    <sfField length="80" n="Email" type="email"/>
    <sfField length="40" n="Phone" type="phone"/>
    <sfField createable="false" editPermission="false" length="40" n="ActivityOriginType" readPermission="false" standardPickListName="Task.ActivityOriginType" t="Activity Origin Type" type="picklist" updateable="false">
      <picklistEntryIds/>
      <picklistEntries/>
    </sfField>
    <sfField createable="false" editPermission="false" n="IsVisibleInSelfService" t="Public" type="_boolean" updateable="false"/>
    <sfField digits="9" n="CallDurationInSeconds" t="Call Duration" type="_int"/>
    <sfField length="40" n="CallType" restrictedPicklist="true" standardPickListName="Task.CallType" t="Call Type" type="picklist">
      <picklistEntryIds>16,17,18</picklistEntryIds>
      <picklistEntries>
        <sfPLE id="16" n="Internal" s=""/>
        <sfPLE id="17" n="Inbound" s=""/>
        <sfPLE id="18" n="Outbound" s=""/>
      </picklistEntries>
    </sfField>
    <sfField length="255" n="CallDisposition" t="Call Result"/>
    <sfField length="255" n="CallObject" t="Call Object Identifier"/>
    <sfField n="ReminderDateTime" t="Reminder Date/Time" type="datetime"/>
    <sfField editPermission="false" n="IsReminderSet" t="Reminder Set" type="_boolean"/>
    <sfField createable="false" length="18" n="RecurrenceActivityId" t="Recurrence Activity" type="reference" updateable="false">
      <referenceTos>
        <string>Task</string>
      </referenceTos>
    </sfField>
    <sfField editPermission="false" n="IsRecurrence" t="Create Recurring Series of Tasks" type="_boolean" updateable="false"/>
    <sfField n="RecurrenceStartDateOnly" t="Recurrence Start" type="date"/>
    <sfField n="RecurrenceEndDateOnly" t="Recurrence End" type="date"/>
    <sfField length="40" n="RecurrenceTimeZoneSidKey" restrictedPicklist="true" standardPickListName="Task.RecurrenceTimeZoneSidKey" t="Recurrence Time Zone" type="picklist">
      <picklistEntryIds>19,20,21,22,23,24,25,26,27,28,29,30,31,32,33,34,35,36,37,38,39,40,41,42,43,44,45,46,47,48,49,50,51,52,53,54,55,56,57,58,59,60,61,62,63,64,65,66,67,68,69,70,71,72,73,74,75,76,77,78,79,80,81,82,83,84,85,86,87,88,89,90,91,92,93,94,95,96,97,98,99,100,101,102,103,104,105,106,107,108,109,110,111,112,113,114,115,116,117</picklistEntryIds>
      <picklistEntries>
        <sfPLE id="19" n="Pacific/Kiritimati" s="" t="(GMT+14:00) Line Is. Time (Pacific/Kiritimati)"/>
        <sfPLE id="20" n="Pacific/Enderbury" s="" t="(GMT+13:00) Phoenix Is. Time (Pacific/Enderbury)"/>
        <sfPLE id="21" n="Pacific/Tongatapu" s="" t="(GMT+13:00) Tonga Time (Pacific/Tongatapu)"/>
        <sfPLE id="22" n="Pacific/Chatham" s="" t="(GMT+12:45) Chatham Standard Time (Pacific/Chatham)"/>
        <sfPLE id="23" n="Asia/Kamchatka" s="" t="(GMT+12:00) Petropavlovsk-Kamchatski Time (Asia/Kamchatka)"/>
        <sfPLE id="24" n="Pacific/Auckland" s="" t="(GMT+12:00) New Zealand Standard Time (Pacific/Auckland)"/>
        <sfPLE id="25" n="Pacific/Fiji" s="" t="(GMT+12:00) Fiji Time (Pacific/Fiji)"/>
        <sfPLE id="26" n="Pacific/Guadalcanal" s="" t="(GMT+11:00) Solomon Is. Time (Pacific/Guadalcanal)"/>
        <sfPLE id="27" n="Pacific/Norfolk" s="" t="(GMT+11:00) Norfolk Time (Pacific/Norfolk)"/>
        <sfPLE id="28" n="Australia/Lord_Howe" s="" t="(GMT+10:30) Lord Howe Standard Time (Australia/Lord_Howe)"/>
        <sfPLE id="29" n="Australia/Brisbane" s="" t="(GMT+10:00) Australian Eastern Standard Time (Queensland) (Australia/Brisbane)"/>
        <sfPLE id="30" n="Australia/Sydney" s="" t="(GMT+10:00) Australian Eastern Standard Time (New South Wales) (Australia/Sydney)"/>
        <sfPLE id="31" n="Australia/Adelaide" s="" t="(GMT+09:30) Australian Central Standard Time (South Australia) (Australia/Adelaide)"/>
        <sfPLE id="32" n="Australia/Darwin" s="" t="(GMT+09:30) Australian Central Standard Time (Northern Territory) (Australia/Darwin)"/>
        <sfPLE id="33" n="Asia/Seoul" s="" t="(GMT+09:00) Korea Standard Time (Asia/Seoul)"/>
        <sfPLE id="34" n="Asia/Tokyo" s="" t="(GMT+09:00) Japan Standard Time (Asia/Tokyo)"/>
        <sfPLE id="35" n="Asia/Hong_Kong" s="" t="(GMT+08:00) Hong Kong Time (Asia/Hong_Kong)"/>
        <sfPLE id="36" n="Asia/Kuala_Lumpur" s="" t="(GMT+08:00) Malaysia Time (Asia/Kuala_Lumpur)"/>
        <sfPLE id="37" n="Asia/Manila" s="" t="(GMT+08:00) Philippines Time (Asia/Manila)"/>
        <sfPLE id="38" n="Asia/Shanghai" s="" t="(GMT+08:00) China Standard Time (Asia/Shanghai)"/>
        <sfPLE id="39" n="Asia/Singapore" s="" t="(GMT+08:00) Singapore Time (Asia/Singapore)"/>
        <sfPLE id="40" n="Asia/Taipei" s="" t="(GMT+08:00) China Standard Time (Asia/Taipei)"/>
        <sfPLE id="41" n="Australia/Perth" s="" t="(GMT+08:00) Australian Western Standard Time (Australia/Perth)"/>
        <sfPLE id="42" n="Asia/Bangkok" s="" t="(GMT+07:00) Indochina Time (Asia/Bangkok)"/>
        <sfPLE id="43" n="Asia/Ho_Chi_Minh" s="" t="(GMT+07:00) Indochina Time (Asia/Ho_Chi_Minh)"/>
        <sfPLE id="44" n="Asia/Jakarta" s="" t="(GMT+07:00) West Indonesia Time (Asia/Jakarta)"/>
        <sfPLE id="45" n="Asia/Rangoon" s="" t="(GMT+06:30) Myanmar Time (Asia/Rangoon)"/>
        <sfPLE id="46" n="Asia/Dhaka" s="" t="(GMT+06:00) Bangladesh Time (Asia/Dhaka)"/>
        <sfPLE id="47" n="Asia/Kathmandu" s="" t="(GMT+05:45) Nepal Time (Asia/Kathmandu)"/>
        <sfPLE id="48" n="Asia/Colombo" s="" t="(GMT+05:30) India Standard Time (Asia/Colombo)"/>
        <sfPLE id="49" n="Asia/Kolkata" s="" t="(GMT+05:30) India Standard Time (Asia/Kolkata)"/>
        <sfPLE id="50" n="Asia/Karachi" s="" t="(GMT+05:00) Pakistan Time (Asia/Karachi)"/>
        <sfPLE id="51" n="Asia/Tashkent" s="" t="(GMT+05:00) Uzbekistan Time (Asia/Tashkent)"/>
        <sfPLE id="52" n="Asia/Yekaterinburg" s="" t="(GMT+05:00) Yekaterinburg Time (Asia/Yekaterinburg)"/>
        <sfPLE id="53" n="Asia/Kabul" s="" t="(GMT+04:30) Afghanistan Time (Asia/Kabul)"/>
        <sfPLE id="54" n="Asia/Tehran" s="" t="(GMT+04:30) Iran Daylight Time (Asia/Tehran)"/>
        <sfPLE id="55" n="Asia/Baku" s="" t="(GMT+04:00) Azerbaijan Time (Asia/Baku)"/>
        <sfPLE id="56" n="Asia/Dubai" s="" t="(GMT+04:00) Gulf Standard Time (Asia/Dubai)"/>
        <sfPLE id="57" n="Asia/Tbilisi" s="" t="(GMT+04:00) Georgia Time (Asia/Tbilisi)"/>
        <sfPLE id="58" n="Asia/Yerevan" s="" t="(GMT+04:00) Armenia Time (Asia/Yerevan)"/>
        <sfPLE id="59" n="Africa/Nairobi" s="" t="(GMT+03:00) Eastern African Time (Africa/Nairobi)"/>
        <sfPLE id="60" n="Asia/Baghdad" s="" t="(GMT+03:00) Arabia Standard Time (Asia/Baghdad)"/>
        <sfPLE id="61" n="Asia/Beirut" s="" t="(GMT+03:00) Eastern European Summer Time (Asia/Beirut)"/>
        <sfPLE id="62" n="Asia/Jerusalem" s="" t="(GMT+03:00) Israel Daylight Time (Asia/Jerusalem)"/>
        <sfPLE id="63" n="Asia/Kuwait" s="" t="(GMT+03:00) Arabia Standard Time (Asia/Kuwait)"/>
        <sfPLE id="64" n="Asia/Riyadh" s="" t="(GMT+03:00) Arabia Standard Time (Asia/Riyadh)"/>
        <sfPLE id="65" n="Europe/Athens" s="" t="(GMT+03:00) Eastern European Summer Time (Europe/Athens)"/>
        <sfPLE id="66" n="Europe/Bucharest" s="" t="(GMT+03:00) Eastern European Summer Time (Europe/Bucharest)"/>
        <sfPLE id="67" n="Europe/Helsinki" s="" t="(GMT+03:00) Eastern European Summer Time (Europe/Helsinki)"/>
        <sfPLE id="68" n="Europe/Istanbul" s="" t="(GMT+03:00) Eastern European Time (Europe/Istanbul)"/>
        <sfPLE id="69" n="Europe/Minsk" s="" t="(GMT+03:00) Moscow Standard Time (Europe/Minsk)"/>
        <sfPLE id="70" n="Europe/Moscow" s="" t="(GMT+03:00) Moscow Standard Time (Europe/Moscow)"/>
        <sfPLE id="71" n="Africa/Cairo" s="" t="(GMT+02:00) Eastern European Time (Africa/Cairo)"/>
        <sfPLE id="72" n="Africa/Johannesburg" s="" t="(GMT+02:00) South Africa Standard Time (Africa/Johannesburg)"/>
        <sfPLE id="73" n="Europe/Amsterdam" s="" t="(GMT+02:00) Central European Summer Time (Europe/Amsterdam)"/>
        <sfPLE id="74" n="Europe/Berlin" s="" t="(GMT+02:00) Central European Summer Time (Europe/Berlin)"/>
        <sfPLE id="75" n="Europe/Brussels" s="" t="(GMT+02:00) Central European Summer Time (Europe/Brussels)"/>
        <sfPLE id="76" n="Europe/Paris" s="" t="(GMT+02:00) Central European Summer Time (Europe/Paris)"/>
        <sfPLE id="77" n="Europe/Prague" s="" t="(GMT+02:00) Central European Summer Time (Europe/Prague)"/>
        <sfPLE id="78" n="Europe/Rome" s="" t="(GMT+02:00) Central European Summer Time (Europe/Rome)"/>
        <sfPLE id="79" n="Africa/Algiers" s="" t="(GMT+01:00) Central European Time (Africa/Algiers)"/>
        <sfPLE id="80" n="Europe/Dublin" s="" t="(GMT+01:00) Irish Summer Time (Europe/Dublin)"/>
        <sfPLE id="81" n="Europe/Lisbon" s="" t="(GMT+01:00) Western European Summer Time (Europe/Lisbon)"/>
        <sfPLE id="82" n="Europe/London" s="" t="(GMT+01:00) British Summer Time (Europe/London)"/>
        <sfPLE id="83" n="Africa/Casablanca" s="" t="(GMT+00:00) Western European Time (Africa/Casablanca)"/>
        <sfPLE id="84" n="America/Scoresbysund" s="" t="(GMT+00:00) Eastern Greenland Summer Time (America/Scoresbysund)"/>
        <sfPLE id="85" n="Atlantic/Azores" s="" t="(GMT+00:00) Azores Summer Time (Atlantic/Azores)"/>
        <sfPLE id="86" n="GMT" s="" t="(GMT+00:00) Greenwich Mean Time (GMT)"/>
        <sfPLE id="87" n="Atlantic/Cape_Verde" s="" t="(GMT-01:00) Cape Verde Time (Atlantic/Cape_Verde)"/>
        <sfPLE id="88" n="Atlantic/South_Georgia" s="" t="(GMT-02:00) South Georgia Standard Time (Atlantic/South_Georgia)"/>
        <sfPLE id="89" n="America/St_Johns" s="" t="(GMT-02:30) Newfoundland Daylight Time (America/St_Johns)"/>
        <sfPLE id="90" n="America/Argentina/Buenos_Aires" s="" t="(GMT-03:00) Argentine Time (America/Argentina/Buenos_Aires)"/>
        <sfPLE id="91" n="America/Halifax" s="" t="(GMT-03:00) Atlantic Daylight Time (America/Halifax)"/>
        <sfPLE id="92" n="America/Sao_Paulo" s="" t="(GMT-03:00) Brasilia Time (America/Sao_Paulo)"/>
        <sfPLE id="93" n="Atlantic/Bermuda" s="" t="(GMT-03:00) Atlantic Daylight Time (Atlantic/Bermuda)"/>
        <sfPLE id="94" n="America/Caracas" s="" t="(GMT-04:00) Venezuela Time (America/Caracas)"/>
        <sfPLE id="95" n="America/Indiana/Indianapolis" s="" t="(GMT-04:00) Eastern Daylight Time (America/Indiana/Indianapolis)"/>
        <sfPLE id="96" n="America/New_York" s="" t="(GMT-04:00) Eastern Daylight Time (America/New_York)"/>
        <sfPLE id="97" n="America/Puerto_Rico" s="" t="(GMT-04:00) Atlantic Standard Time (America/Puerto_Rico)"/>
        <sfPLE id="98" n="America/Santiago" s="" t="(GMT-04:00) Chile Time (America/Santiago)"/>
        <sfPLE id="99" n="America/Bogota" s="" t="(GMT-05:00) Colombia Time (America/Bogota)"/>
        <sfPLE id="100" n="America/Chicago" s="" t="(GMT-05:00) Central Daylight Time (America/Chicago)"/>
        <sfPLE id="101" n="America/Lima" s="" t="(GMT-05:00) Peru Time (America/Lima)"/>
        <sfPLE id="102" n="America/Mexico_City" s="" t="(GMT-05:00) Central Daylight Time (America/Mexico_City)"/>
        <sfPLE id="103" n="America/Panama" s="" t="(GMT-05:00) Eastern Standard Time (America/Panama)"/>
        <sfPLE id="104" n="America/Denver" s="" t="(GMT-06:00) Mountain Daylight Time (America/Denver)"/>
        <sfPLE id="105" n="America/El_Salvador" s="" t="(GMT-06:00) Central Standard Time (America/El_Salvador)"/>
        <sfPLE id="106" n="America/Mazatlan" s="" t="(GMT-06:00) Mountain Daylight Time (America/Mazatlan)"/>
        <sfPLE id="107" n="America/Los_Angeles" s="" t="(GMT-07:00) Pacific Daylight Time (America/Los_Angeles)"/>
        <sfPLE id="108" n="America/Phoenix" s="" t="(GMT-07:00) Mountain Standard Time (America/Phoenix)"/>
        <sfPLE id="109" n="America/Tijuana" s="" t="(GMT-07:00) Pacific Daylight Time (America/Tijuana)"/>
        <sfPLE id="110" n="America/Anchorage" s="" t="(GMT-08:00) Alaska Daylight Time (America/Anchorage)"/>
        <sfPLE id="111" n="Pacific/Pitcairn" s="" t="(GMT-08:00) Pitcairn Standard Time (Pacific/Pitcairn)"/>
        <sfPLE id="112" n="America/Adak" s="" t="(GMT-09:00) Hawaii-Aleutian Daylight Time (America/Adak)"/>
        <sfPLE id="113" n="Pacific/Gambier" s="" t="(GMT-09:00) Gambier Time (Pacific/Gambier)"/>
        <sfPLE id="114" n="Pacific/Marquesas" s="" t="(GMT-09:30) Marquesas Time (Pacific/Marquesas)"/>
        <sfPLE id="115" n="Pacific/Honolulu" s="" t="(GMT-10:00) Hawaii-Aleutian Standard Time (Pacific/Honolulu)"/>
        <sfPLE id="116" n="Pacific/Niue" s="" t="(GMT-11:00) Niue Time (Pacific/Niue)"/>
        <sfPLE id="117" n="Pacific/Pago_Pago" s="" t="(GMT-11:00) Samoa Standard Time (Pacific/Pago_Pago)"/>
      </picklistEntries>
    </sfField>
    <sfField length="40" n="RecurrenceType" restrictedPicklist="true" standardPickListName="Task.RecurrenceType" t="Recurrence Type" type="picklist">
      <picklistEntryIds>118,119,120,121,122,123,124</picklistEntryIds>
      <picklistEntries>
        <sfPLE id="118" n="RecursDaily" s="" t="Recurs Daily"/>
        <sfPLE id="119" n="RecursEveryWeekday" s="" t="Recurs Every Weekday"/>
        <sfPLE id="120" n="RecursMonthly" s="" t="Recurs Monthly"/>
        <sfPLE id="121" n="RecursMonthlyNth" s="" t="Recurs Monthy Nth"/>
        <sfPLE id="122" n="RecursWeekly" s="" t="Recurs Weekly"/>
        <sfPLE id="123" n="RecursYearly" s="" t="Recurs Yearly"/>
        <sfPLE id="124" n="RecursYearlyNth" s="" t="Recurs Yearly Nth"/>
      </picklistEntries>
    </sfField>
    <sfField digits="9" n="RecurrenceInterval" t="Recurrence Interval" type="_int"/>
    <sfField digits="9" n="RecurrenceDayOfWeekMask" t="Recurrence Day of Week Mask" type="_int"/>
    <sfField digits="9" n="RecurrenceDayOfMonth" t="Recurrence Day of Month" type="_int"/>
    <sfField length="40" n="RecurrenceInstance" restrictedPicklist="true" standardPickListName="Task.RecurrenceInstance" t="Recurrence Instance" type="picklist">
      <picklistEntryIds>125,126,127,128,129</picklistEntryIds>
      <picklistEntries>
        <sfPLE id="125" n="First" s="" t="1st"/>
        <sfPLE id="126" n="Second" s="" t="2nd"/>
        <sfPLE id="127" n="Third" s="" t="3rd"/>
        <sfPLE id="128" n="Fourth" s="" t="4th"/>
        <sfPLE id="129" n="Last" s="" t="last"/>
      </picklistEntries>
    </sfField>
    <sfField length="40" n="RecurrenceMonthOfYear" restrictedPicklist="true" standardPickListName="Task.RecurrenceMonthOfYear" t="Recurrence Month of Year" type="picklist">
      <picklistEntryIds>130,131,132,133,134,135,136,137,138,139,140,141</picklistEntryIds>
      <picklistEntries>
        <sfPLE id="130" n="January" s=""/>
        <sfPLE id="131" n="February" s=""/>
        <sfPLE id="132" n="March" s=""/>
        <sfPLE id="133" n="April" s=""/>
        <sfPLE id="134" n="May" s=""/>
        <sfPLE id="135" n="June" s=""/>
        <sfPLE id="136" n="July" s=""/>
        <sfPLE id="137" n="August" s=""/>
        <sfPLE id="138" n="September" s=""/>
        <sfPLE id="139" n="October" s=""/>
        <sfPLE id="140" n="November" s=""/>
        <sfPLE id="141" n="December" s=""/>
      </picklistEntries>
    </sfField>
    <sfField length="40" n="RecurrenceRegeneratedType" restrictedPicklist="true" standardPickListName="Task.RecurrenceRegeneratedType" t="Repeat This Task" type="picklist">
      <picklistEntryIds>142,143,144</picklistEntryIds>
      <picklistEntries>
        <sfPLE id="142" n="RecurrenceRegenerateAfterDueDate" s="" t="After due date"/>
        <sfPLE id="143" n="RecurrenceRegenerateAfterToday" s="" t="After date completed"/>
        <sfPLE id="144" n="RecurrenceRegenerated" s="" t="(Task Closed)"/>
      </picklistEntries>
    </sfField>
    <sfField length="40" n="TaskSubtype" restrictedPicklist="true" standardPickListName="Task.TaskSubtype" t="Task Subtype" type="picklist" updateable="false">
      <picklistEntryIds>145,146,147,148</picklistEntryIds>
      <picklistEntries>
        <sfPLE id="145" n="Task" s=""/>
        <sfPLE id="146" n="Email" s=""/>
        <sfPLE id="147" n="ListEmail" s="" t="List Email"/>
        <sfPLE id="148" n="Call" s=""/>
      </picklistEntries>
    </sfField>
    <sfField createable="false" editPermission="false" n="CompletedDateTime" readPermission="false" t="Completed Date" type="datetime" updateable="false"/>
    <sfField editPermission="false" n="Delta_Data_Migration__c" t="Delta Data Migration" type="_boolean"/>
    <sfField editPermission="false" length="40" n="DM_External_ID__c" t="DM External ID"/>
    <sfField editPermission="false" length="150" n="Source_System__c" t="Source System"/>
    <sfField editPermission="false" length="120" n="DM_Legacy_Owner_Name__c" readPermission="false" t="DM Legacy Owner Name"/>
    <sfField editPermission="false" length="18" n="sked__Activity__c" readPermission="false" relationshipLabel="Activities" relationshipName="sked__Activity__r" t="Activity" type="reference">
      <referenceTos>
        <string>sked__Activity__c</string>
      </referenceTos>
    </sfField>
    <sfField editPermission="false" length="18" n="sked__Job_Allocation__c" readPermission="false" relationshipLabel="Activities" relationshipName="sked__Job_Allocation__r" t="Job Allocation" type="reference">
      <referenceTos>
        <string>sked__Job_Allocation__c</string>
      </referenceTos>
    </sfField>
    <sfField editPermission="false" length="20" n="ACD_Queue__c" readPermission="false" t="ACD Queue"/>
    <sfField editPermission="false" length="20" n="Agent_ID__c" readPermission="false" t="Agent ID"/>
    <sfField editPermission="false" length="9" n="Call_ID__c" readPermission="false" t="Call ID"/>
    <sfField editPermission="false" n="Call_Start_Time__c" readPermission="false" t="Call Start Time" type="datetime"/>
    <sfField editPermission="false" length="40" n="Called__c" readPermission="false" t="Called" type="phone"/>
    <sfField editPermission="false" length="40" n="Caller__c" readPermission="false" t="Caller" type="phone"/>
    <sfField editPermission="false" length="9" n="Old_Call_ID__c" readPermission="false" t="Old Call ID"/>
    <sfField editPermission="false" length="20" n="Original_Call_Object_ID__c" readPermission="false" t="Original Call Object ID"/>
    <sfField editPermission="false" length="96" n="POM_Campaign__c" readPermission="false" t="POM Campaign"/>
    <sfField editPermission="false" length="96" n="UUI__c" readPermission="false" t="UUI"/>
    <sfField editPermission="false" length="255" n="Call_Result_Detail_1__c" readPermission="false" t="Call Result Detail 1" type="picklist">
      <picklistEntryIds>149,150,151,152,153,154,155,156,157,158,159,160,161</picklistEntryIds>
      <picklistEntries>
        <sfPLE id="149" n="ARC AP" s=""/>
        <sfPLE id="150" n="Closed Failed to Connect" s=""/>
        <sfPLE id="151" n="Community" s=""/>
        <sfPLE id="152" n="Competitor" s=""/>
        <sfPLE id="153" n="Date Availability" s=""/>
        <sfPLE id="154" n="Escalated" s=""/>
        <sfPLE id="155" n="Local Rep" s=""/>
        <sfPLE id="156" n="Not Interested / No Reason Given" s=""/>
        <sfPLE id="157" n="Price" s=""/>
        <sfPLE id="158" n="Recently Certified" s=""/>
        <sfPLE id="159" n="Referred" s=""/>
        <sfPLE id="160" n="Bad Contact Info" s=""/>
        <sfPLE id="161" n="Other" s=""/>
      </picklistEntries>
    </sfField>
    <sfField editPermission="false" length="255" n="Call_Result_Detail_2__c" readPermission="false" t="Call Result Detail 2" type="picklist">
      <picklistEntryIds>162,163,164,165,166,167,168,169,170,171,172,173,174,175,176,177,178,179,180,181,182,183,184,185,186,187,188,189,190</picklistEntryIds>
      <picklistEntries>
        <sfPLE id="162" n="Date" s=""/>
        <sfPLE id="163" n="Group Size" s=""/>
        <sfPLE id="164" n="Price" s=""/>
        <sfPLE id="165" n="NAN" s=""/>
        <sfPLE id="166" n="AP" s=""/>
        <sfPLE id="167" n="Other" s=""/>
        <sfPLE id="168" n="Full Service" s=""/>
        <sfPLE id="169" n="Shopping" s=""/>
        <sfPLE id="170" n="Too High" s=""/>
        <sfPLE id="171" n="Budget" s=""/>
        <sfPLE id="172" n="ARC AP" s=""/>
        <sfPLE id="173" n="ARC Community" s=""/>
        <sfPLE id="174" n="ARC Full Service" s=""/>
        <sfPLE id="175" n="Competitor - AP" s=""/>
        <sfPLE id="176" n="Competitor - Full Service" s=""/>
        <sfPLE id="177" n="Competitor - Group Size" s=""/>
        <sfPLE id="178" n="Local Rep" s=""/>
        <sfPLE id="179" n="ARC Community - Group Size" s=""/>
        <sfPLE id="180" n="ARC Community - Other" s=""/>
        <sfPLE id="181" n="ARC Community - Price" s=""/>
        <sfPLE id="182" n="Demo - No Fee Class" s=""/>
        <sfPLE id="183" n="Field Non BGST Class" s=""/>
        <sfPLE id="184" n="FO Other" s=""/>
        <sfPLE id="185" n="RCO Website" s=""/>
        <sfPLE id="186" n="Pending Agreement/Proposal" s=""/>
        <sfPLE id="187" n="Out of Business" s=""/>
        <sfPLE id="188" n="Wrong Email" s=""/>
        <sfPLE id="189" n="Wrong Phone Number" s=""/>
        <sfPLE id="190" n="Wrong POC" s=""/>
      </picklistEntries>
    </sfField>
    <sfField editPermission="false" length="255" n="Call_Result__c" readPermission="false" t="Call Result" type="picklist">
      <picklistEntryIds>191,192,193,194,195,196,197,198,199</picklistEntryIds>
      <picklistEntries>
        <sfPLE id="191" n="Open - Not Yet Worked" s=""/>
        <sfPLE id="192" n="Opportunity" s=""/>
        <sfPLE id="193" n="Sale" s=""/>
        <sfPLE id="194" n="No Sale" s=""/>
        <sfPLE id="195" n="No Opportunity" s=""/>
        <sfPLE id="196" n="Not Interested - No Reason Given" s=""/>
        <sfPLE id="197" n="Aged Pipeline Lead" s=""/>
        <sfPLE id="198" n="Cancellation" s=""/>
        <sfPLE id="199" n="Duplicate" s=""/>
      </picklistEntries>
    </sfField>
    <sfField editPermission="false" length="255" n="Call_Source__c" readPermission="false" t="Call Source" type="picklist">
      <picklistEntryIds>200,201,202,203,204,205,206</picklistEntryIds>
      <picklistEntries>
        <sfPLE id="200" n="IVR" s=""/>
        <sfPLE id="201" n="TSC Transfer" s=""/>
        <sfPLE id="202" n="Email" s=""/>
        <sfPLE id="203" n="Voice Mail" s=""/>
        <sfPLE id="204" n="After-Hours Transfer Lead Form" s=""/>
        <sfPLE id="205" n="Referral/Repeat Business" s=""/>
        <sfPLE id="206" n="Marketing" s=""/>
      </picklistEntries>
    </sfField>
    <sfField calculated="true" createable="false" editPermission="false" formula="$Profile.Name" formulaTreatBlanksAs="BlankAsZero" length="1300" n="Owner_Profile__c" readPermission="false" t="Owner Profile" updateable="false"/>
    <sfField calculated="true" createable="false" editPermission="false" formula="CASE(LEFT(WhatId,3), &quot;001&quot;,&quot;Account&quot;, &quot;006&quot;,&quot;Opportunity&quot;, &quot;500&quot;,&quot;Case&quot;, CASE(LEFT(WhoId,3), &quot;003&quot;,&quot;Contact&quot;, &quot;00Q&quot;,&quot;Lead&quot;, NULL))" length="1300" n="Activity_On__c" readPermission="false" t="Activity On" updateable="false"/>
  </fields>
  <childRelationships>
    <sfObjectRelationship alias="RelatedActivityAttachmentList" childName="Attachment" field="ParentId" n="Attachments" relationshipName="Attachments" s="2-" t="Attachment"/>
    <sfObjectRelationship childName="ContentDocumentLink" field="LinkedEntityId" n="ContentDocumentLinks" relationshipName="ContentDocumentLinks" s="2-" t="ContentDocumentLink"/>
    <sfObjectRelationship alias="RelatedFileList" childName="AttachedContentDocument" field="LinkedEntityId" n="AttachedContentDocuments" relationshipName="AttachedContentDocuments" s="2-" t="AttachedContentDocument"/>
    <sfObjectRelationship alias="RelatedNoteList" childName="CombinedAttachment" field="ParentId" n="CombinedAttachments" relationshipName="CombinedAttachments" s="2-" t="CombinedAttachment"/>
    <sfObjectRelationship childName="EntitySubscription" field="ParentId" n="FeedSubscriptionsForEntity" relationshipName="FeedSubscriptionsForEntity" s="2-" t="EntitySubscription"/>
    <sfObjectRelationship childName="Task" field="RecurrenceActivityId" n="RecurringTasks" relationshipName="RecurringTasks" s="2-" t="Task"/>
    <sfObjectRelationship childName="TaskRelation" field="TaskId" n="TaskRelations" relationshipName="TaskRelations" s="2-" t="TaskRelation"/>
    <sfObjectRelationship childName="TaskWhoRelation" field="TaskId" n="TaskWhoRelations" relationshipName="TaskWhoRelations" s="2-" t="TaskWhoRelation"/>
    <sfObjectRelationship childName="TopicAssignment" field="EntityId" n="TopicAssignments" relationshipName="TopicAssignments" s="2-" t="TopicAssignment"/>
    <sfObjectRelationship alias="RelatedContentNoteList" childName="AttachedContentNote" field="LinkedEntityId" n="AttachedContentNotes" relationshipName="AttachedContentNotes" s="2-" t="AttachedContentNote"/>
    <sfObjectRelationship childName="NetworkActivityAudit" field="ParentEntityId" n="ParentEntities" relationshipName="ParentEntities" s="2-" t="NetworkActivityAudit"/>
    <sfObjectRelationship childName="NetworkUserHistoryRecent" field="RecordId" n="NetworkUserHistoryRecentToRecord" relationshipName="NetworkUserHistoryRecentToRecord" s="2-" t="NetworkUserHistoryRecent"/>
    <sfObjectRelationship childName="SurveySubject" field="SubjectId" n="SurveySubjectEntities" relationshipName="SurveySubjectEntities" s="2-" t="SurveySubject"/>
    <sfObjectRelationship childName="TaskFeed" field="ParentId" n="Feeds" relationshipName="Feeds" s="2-" t="TaskFeed"/>
  </childRelationships>
  <recordTypes>
    <sfRecordType layoutsLoaded="false" n="&lt;default&gt;" t="Web Record Type Mapping"/>
  </recordTypes>
  <standardActions>
    <sfActionLink modes="ObjectHome Tasks List RecurringTasks" n="New"/>
    <sfActionLink modes="View Tasks Activity.Campaign_Call_List__c RecurringTasks" n="Edit" requiresRow="true" s="2"/>
    <sfActionLink modes="View Tasks Activity.Campaign_Call_List__c RecurringTasks" n="Delete" requiresRow="true" s="3" t="Del"/>
    <sfActionLink lightningActionName="MassChangeOwner" massAction="true" modes="View List all_related_lists" n="ChangeOwnerOne" t="Change Owner"/>
    <sfActionLink modes="View Tasks RecurringTasks" n="ShowMore" t="Show More"/>
    <sfActionLink modes="View Tasks RecurringTasks" n="GoToList" t="Go To List"/>
    <sfActionLink modes="RelatedList" n="PrevPage" t="Previous Page"/>
    <sfActionLink modes="RelatedList" n="NextPage" t="Next Page"/>
    <sfActionLink n="NewTask" s="" t="New Task"/>
    <sfActionLink n="Close" requiresRow="true" s="3"/>
    <sfActionLink modes="View" n="ChangeTaskStatus" t="Mark Complete/Reopen"/>
    <sfActionLink modes="ObjectHome" n="View" requiresRow="true"/>
    <sfActionLink n="DeleteSeries" s="" t="Delete Series"/>
    <sfActionLink n="ViewSeries" s="" t="View Series"/>
    <sfActionLink buttonName="SDOC__S_Docs" n="SDOC__S_Docs" s="" t="S-Docs"/>
    <sfActionLink buttonName="MA_MapIt_a0Rd00000006eWlEAI" n="MA_MapIt_a0Rd00000006eWlEAI" s="" t="Map It"/>
    <sfActionLink modes="View" n="Clone" requiresRow="true"/>
    <sfActionLink modes="View Submit" n="Submit" requiresRow="true"/>
    <sfActionLink modes="View Remove" n="Remove"/>
    <sfActionLink modes="View Unlock" n="Unlock" t="Unlock Record"/>
    <sfActionLink modes="ObjectHome" n="List" requiresRow="true"/>
    <sfActionLink modes="Edit New Clone" n="save" requiresRow="true" t="Save"/>
    <sfActionLink modes="Edit New Clone" n="save_new" requiresRow="true" t="Save and New"/>
    <sfActionLink modes="Edit New Clone" n="cancel" requiresRow="true" t="Cancel"/>
    <sfActionLink afterWaitUrl="ui:wait:timed?seconds=10" modes="View" n="SaveEdit" t="Save"/>
    <sfActionLink modes="View" n="CancelEdit" t="Cancel"/>
    <sfActionLink massAction="true" modes="View List" n="ChangeRecordType" t="Change Record Type"/>
    <sfActionLink modes="View" n="email" t="Send an Email"/>
    <sfActionLink modes="View" n="Share"/>
    <sfActionLink modes="QuickAction" n="publishersharebutton" t="Create"/>
    <sfActionLink modes="ObjectHome List" n="Sort"/>
    <sfActionLink modes="ObjectHome List" n="Filter"/>
    <sfActionLink modes="ObjectHome View" n="Search"/>
    <sfActionLink modes="ObjectHome List" n="Import"/>
    <sfActionLink modes="View" n="PrintableView" t="Printable View"/>
    <sfActionLink n="ObjectHome" requiresRow="true" t="Home"/>
    <sfActionLink modes="Edit New Clone" n="savenewtask" t="Save and New Task"/>
    <sfActionLink modes="Edit New Clone" n="savenewevent" t="Save and New Event"/>
    <sfActionLink lightningActionName="FollowupEvent" modes="View tasks" n="newEvent" t="Create Follow-Up Event"/>
    <sfActionLink modes="tasks" n="Task.EditDescription" requiresRow="true" s="2" t="Edit Comments"/>
    <sfActionLink modes="tasks" n="Task.Defer" requiresRow="true" s="2" t="Change Date"/>
    <sfActionLink modes="tasks" n="FollowupTask" requiresRow="true" s="2" t="Create Follow-Up Task"/>
    <sfActionLink modes="tasks" n="Task.UpdateStatus" requiresRow="true" s="2" t="Change Status"/>
    <sfActionLink modes="tasks" n="Task.UpdatePriority" requiresRow="true" s="2" t="Change Priority"/>
  </standardActions>
  <homeListColumns>
    <string>TASK.NAME</string>
  </homeListColumns>
  <lookupColumns>
    <string>TASK.NAME</string>
  </lookupColumns>
  <weblinks/>
  <searchResultColumns>
    <string>TASK.NAME</string>
  </searchResultColumns>
  <compactLayoutFields>
    <string>Subject</string>
    <string>WhoId</string>
    <string>WhatId</string>
  </compactLayoutFields>
  <listViewActions/>
</sfObject>
